pdf2bib/__init__.py
pdf2bib/bibtex_makers.py
pdf2bib/config.py
pdf2bib/main.py
pdf2bib/utils_registry.py
pdf2bib-1.2.dist-info/METADATA
pdf2bib-1.2.dist-info/WHEEL
pdf2bib-1.2.dist-info/entry_points.txt
pdf2bib-1.2.dist-info/top_level.txt
pdf2bib-1.2.dist-info/RECORD
