Metadata-Version: 2.1
Name: pdf2bib
Version: 1.2
Summary: A  python library/command-line tool to quickly and automatically generate BibTeX data starting from the pdf file of a scientific publication.
Home-page: https://github.com/MicheleCotrufo/pdf2bib
Author: Michele Cotrufo
Author-email: michele.cotrufo@gmail.com
License: MIT
Platform: UNKNOWN
Requires-Dist: bibtexparser (>=1.2.0)
Requires-Dist: pyperclip
Requires-Dist: unidecode
Requires-Dist: pdf2doi (>=1.6)
